{
  "saintsCategory": [
    { "name": "BronzeSaints", "image": "BronzeSaints", "path": "/characters/Bronze" },
    { "name": "BlackSaints", "image": "BlackSaints", "path": "/characters/Black" },
    { "name": "SilverSaints", "image": "SilverSaints", "path": "/characters/Silver" },
    { "name": "GoldSaints", "image": "GoldSaints", "path": "/characters/Gold" },
    { "name": "AsgardWarriors", "image": "AsgardWarriors", "path": "/characters/Asgard" },
    { "name": "PoseidonScales", "image": "PoseidonScales", "path": "/characters/Poseidon" }
  ],
  "features": [
    { "label": "Name", "key": "name" },
    { "label": "Country", "key": "country" },
    { "label": "Age", "key": "age" },
    { "label": "Height", "key": "height" },
    { "label": "Weight", "key": "weight" },
    { "label": "Cloth", "key": "cloth" }
  ],
  "bronze": [
    {
      "name": "Seiya",
      "country": "Japan",
      "age": "13",
      "height": "1.65cm",
      "weight": "53kg",
      "cloth": "Pegasus",
      "attacks": ["Pegasus Meteor Fist", "Pegasus Comet Fist"],
      "source": "Seiya",
      "type": "bronze"
    },
    {
      "name": "Shiryu",
      "country": "China",
      "age": "14",
      "height": "1.72cm",
      "weight": "53kg",
      "cloth": "Dragon",
      "attacks": ["Rozan Rising Dragon", "Rozan Flying Dragon"],
      "source": "Shiryu",
      "type": "bronze"
    },
    {
      "name": "Hyoga",
      "country": "Russia",
      "age": "14",
      "height": "1.73cm",
      "weight": "60kg",
      "cloth": "Cygnus",
      "attacks": ["Diamond Dust", "Aurora Thunder Attack"],
      "source": "Hyoga",
      "type": "bronze"
    },
    {
      "name": "Shun",
      "country": "Japan",
      "age": "13",
      "height": "1.65cm",
      "weight": "51kg",
      "cloth": "Andromeda",
      "attacks": ["Nebula Chain", "Rolling Defense"],
      "source": "Shun",
      "type": "bronze"
    },
    {
      "name": "Ikki",
      "country": "Japan",
      "age": "15",
      "height": "1.75cm",
      "weight": "62kg",
      "cloth": "Phoenix",
      "attacks": ["Phoenix's Wings Rise", "Phoenix's Illusion Demon Fist"],
      "source": "Ikki",
      "type": "bronze"
    },
    {
      "name": "Jabu",
      "country": "Japan",
      "age": "13",
      "height": "1.65cm",
      "weight": "55kg",
      "cloth": "Unicorn",
      "attacks": ["Unicorn Gallop"],
      "source": "Jabu",
      "type": "bronze"
    },
    {
      "name": "Ban",
      "country": "Japan",
      "age": "14",
      "height": "1.81cm",
      "weight": "83kg",
      "cloth": "Lionet",
      "attacks": ["Lionet Bomber"],
      "source": "Ban",
      "type": "bronze"
    },
    {
      "name": "Geki",
      "country": "Japan",
      "age": "15",
      "height": "1.88cm",
      "weight": "102kg",
      "cloth": "Bear",
      "attacks": ["Hanging Bear"],
      "source": "Geki",
      "type": "bronze"
    },
    {
      "name": "Ichi",
      "country": "Japan",
      "age": "14",
      "height": "1.70cm",
      "weight": "56kg",
      "cloth": "Hydra",
      "attacks": ["Hydra Fangs"],
      "source": "Ichi",
      "type": "bronze"
    },
    {
      "name": "Nachi",
      "country": "Japan",
      "age": "14",
      "height": "1.71cm",
      "weight": "57kg",
      "cloth": "Wolf",
      "attacks": ["Dead Howling"],
      "source": "Nachi",
      "type": "bronze"
    }
  ],
  "black": [
    {
      "name": "BlackPegasus",
      "country": "Israel",
      "age": "15",
      "height": "1.70cm",
      "weight": "58kg",
      "cloth": "BlackPegasus",
      "attacks": ["Black Meteor Fist"],
      "source": "PegasusBlack",
      "type": "black"
    },
    {
      "name": "BlackDragon",
      "country": "Poland",
      "age": "15",
      "height": "1.73cm",
      "weight": "62kg",
      "cloth": "BlackDragon",
      "attacks": ["Black Rising Dragon"],
      "source": "DragonBlack",
      "type": "black"
    },
    {
      "name": "BlackCygnus",
      "country": "Finland",
      "age": "15",
      "height": "1.73cm",
      "weight": "61kg",
      "cloth": "BlackCygnus",
      "attacks": ["Black Blizzard"],
      "source": "CygnusBlack",
      "type": "black"
    },
    {
      "name": "BlackAndromeda",
      "country": "Turkey",
      "age": "14",
      "height": "1.70cm",
      "weight": "58kg",
      "cloth": "BlackAndromeda",
      "attacks": ["Black Fang Nebula"],
      "source": "AndromedaBlack",
      "type": "black"
    },
    {
      "name": "BlackPhoenix",
      "country": "unknown",
      "age": "unknown",
      "height": "unknown",
      "weight": "unknown",
      "cloth": "BlackPhoenix",
      "attacks": ["Black Phoenix Illusion"],
      "source": "PhoenixBlack",
      "type": "black"
    }
  ]
}